metasub_utils/cli.py
metasub_utils-0.9.0.dist-info/METADATA
metasub_utils-0.9.0.dist-info/RECORD
metasub_utils-0.9.0.dist-info/WHEEL
metasub_utils-0.9.0.dist-info/entry_points.txt
metasub_utils-0.9.0.dist-info/top_level.txt
