Metadata-Version: 2.1
Name: metasub-utils
Version: 0.9.0
Summary: Utility functions for the MetaSUB Consortium
Home-page: UNKNOWN
Author: David Danko
Author-email: dcdanko@gmail.com
License: MIT License
Platform: UNKNOWN
Classifier: License :: OSI Approved :: MIT License
Classifier: Natural Language :: English
Classifier: Programming Language :: Python :: 3.6
Requires-Dist: future
Requires-Dist: six
Requires-Dist: metasub-utils.athena
Requires-Dist: metasub-utils.bridges
Requires-Dist: metasub-utils.hudson-alpha
Requires-Dist: metasub-utils.metadata (>=0.3.1)
Requires-Dist: metasub-utils.metagenscope
Requires-Dist: metasub-utils.wasabi (>=0.7.0)
Requires-Dist: metasub-utils.zurich
Requires-Dist: metasub-utils.packet-parse (>=0.1.6)
Requires-Dist: metasub-utils.data-packet (>=0.3.0)
